jupyter_http_manager/__init__.py
jupyter_http_manager/main.py
jupyter_http_manager/plugin.py
jupyter_http_manager/schema.py
jupyter_http_manager/webapi/dependencies.py
jupyter_http_manager/webapi/lifespan.py
jupyter_http_manager/webapi/logger.py
jupyter_http_manager/webapi/main.py
jupyter_http_manager/webapi/schema.py
jupyter_http_manager/webapi/socket.py
jupyter_http_manager/webapi/state.py
jupyter_http_manager-0.1.1.dist-info/METADATA
jupyter_http_manager-0.1.1.dist-info/WHEEL
jupyter_http_manager-0.1.1.dist-info/entry_points.txt
jupyter_http_manager-0.1.1.dist-info/RECORD
