Metadata-Version: 2.1
Name: jupyter_http_manager
Version: 0.1.1
Summary: 
Author: Evan Voyles
Author-email: ejovo13@yahoo.com
Requires-Python: >=3.11,<4.0
Classifier: Programming Language :: Python :: 3
Classifier: Programming Language :: Python :: 3.11
Classifier: Programming Language :: Python :: 3.12
Requires-Dist: fastapi[uvicorn] (>=0.115.6,<0.116.0)
Requires-Dist: jupyter-client (>=8.6.3,<9.0.0)
Requires-Dist: nbformat (>=5.10.4,<6.0.0)
Requires-Dist: orjson (>=3.10.12,<4.0.0)
Requires-Dist: pydantic (>=2.10.4,<3.0.0)
Requires-Dist: pynvim (>=0.5.2,<0.6.0)
Requires-Dist: python-json-logger (>=3.2.1,<4.0.0)
Requires-Dist: rich (>=13.9.4,<14.0.0)
Requires-Dist: typer (>=0.15.1,<0.16.0)
Requires-Dist: uvicorn (>=0.34.0,<0.35.0)
Requires-Dist: uvloop (>=0.21.0,<0.22.0)
